kozmoml_supervisor_detect/__init__.py
kozmoml_supervisor_detect/runtime.py
kozmoml_supervisor_detect/version.py
kozmoml_supervisor_detect-0.1.0.dev1.dist-info/LICENSE
kozmoml_supervisor_detect-0.1.0.dev1.dist-info/METADATA
kozmoml_supervisor_detect-0.1.0.dev1.dist-info/WHEEL
kozmoml_supervisor_detect-0.1.0.dev1.dist-info/RECORD
